{
  "plugins": {
    "vim-abolish": {
      "rev": "dcbfe065297d31823561ba787f51056c147aa682",
      "src": "https://github.com/tpope/vim-abolish"
    },
    "vim-commentary": {
      "rev": "64a654ef4a20db1727938338310209b6a63f60c9",
      "src": "https://github.com/tpope/vim-commentary"
    },
    "vim-eunuch": {
      "rev": "e86bb794a1c10a2edac130feb0ea590a00d03f1e",
      "src": "https://github.com/tpope/vim-eunuch"
    },
    "vim-fugitive": {
      "rev": "3b753cf8c6a4dcde6edee8827d464ba9b8c4a6f0",
      "src": "https://github.com/tpope/vim-fugitive"
    },
    "vim-repeat": {
      "rev": "65846025c15494983dafe5e3b46c8f88ab2e9635",
      "src": "https://github.com/tpope/vim-repeat"
    },
    "vim-sleuth": {
      "rev": "be69bff86754b1aa5adcbb527d7fcd1635a84080",
      "src": "https://github.com/tpope/vim-sleuth"
    },
    "vim-surround": {
      "rev": "3d188ed2113431cf8dac77be61b842acb64433d9",
      "src": "https://github.com/tpope/vim-surround"
    }
  }
}
